shelloracle/__init__.py
shelloracle/__main__.py
shelloracle/bootstrap.py
shelloracle/config.py
shelloracle/py.typed
shelloracle/shelloracle.py
shelloracle/tty_log_handler.py
shelloracle/cli/__init__.py
shelloracle/cli/application.py
shelloracle/cli/config/__init__.py
shelloracle/cli/config/edit.py
shelloracle/cli/config/init.py
shelloracle/providers/__init__.py
shelloracle/providers/deepseek.py
shelloracle/providers/google.py
shelloracle/providers/localai.py
shelloracle/providers/ollama.py
shelloracle/providers/openai.py
shelloracle/providers/openai_compat.py
shelloracle/providers/xai.py
shelloracle/shell/shelloracle.bash
shelloracle/shell/shelloracle.fish
shelloracle/shell/shelloracle.zsh
shelloracle-1.9.0.dist-info/METADATA
shelloracle-1.9.0.dist-info/WHEEL
shelloracle-1.9.0.dist-info/entry_points.txt
shelloracle-1.9.0.dist-info/licenses/LICENSE
shelloracle-1.9.0.dist-info/RECORD
