Metadata-Version: 2.4
Name: shelloracle
Version: 1.9.0
Summary: ShellOracle is a pluggable terminal utility that takes a natural language description of a command and substitutes it into your terminal buffer.
Project-URL: Homepage, https://github.com/djcopley/ShellOracle
Project-URL: Repository, https://github.com/djcopley/ShellOracle.git
Project-URL: Issues, https://github.com/djcopley/ShellOracle/issues
Author-email: Daniel Copley <djcopley@proton.me>
License:                     GNU GENERAL PUBLIC LICENSE
License-File: LICENSE
Classifier: Development Status :: 5 - Production/Stable
Classifier: Environment :: Console
Classifier: Intended Audience :: Developers
Classifier: License :: OSI Approved :: GNU General Public License v3 (GPLv3)
Classifier: Operating System :: MacOS
Classifier: Operating System :: POSIX :: Linux
Classifier: Programming Language :: Python :: 3
Classifier: Programming Language :: Python :: 3.9
Classifier: Programming Language :: Python :: 3.10
Classifier: Programming Language :: Python :: 3.11
Classifier: Programming Language :: Python :: 3.12
Classifier: Programming Language :: Python :: 3.13
Requires-Python: >=3.9
Requires-Dist: click~=8.1
Requires-Dist: dspy~=2.6
Requires-Dist: google-generativeai~=0.8
Requires-Dist: httpx~=0.28
Requires-Dist: openai~=1.66
Requires-Dist: prompt-toolkit~=3.0
Requires-Dist: tomli~=2.1; python_version < '3.11'
Requires-Dist: tomlkit~=0.13
Requires-Dist: yaspin~=3.1
